README.rst
polyglot.py
setup.py
polyglot_code.egg-info/PKG-INFO
polyglot_code.egg-info/SOURCES.txt
polyglot_code.egg-info/dependency_links.txt
polyglot_code.egg-info/top_level.txt