Metadata-Version: 1.2
Name: polyglot-code
Version: 1.0.10
Summary: Write console logs in 'any' programming language
Home-page: https://github.com/cosasdepuma
Author: Kike Fontan (@CosasDePuma)
Author-email: kikefontanlorenzo@gmail.com
Maintainer: Kike Fontan (@CosasDePuma)
Maintainer-email: kikefontanlorenzo@gmail.com
License: Apache-2.0
Keywords: log,debug,console,anyprint,polyglot
Platform: UNKNOWN
